axpsystems/__init__.py
axpsystems-0.0.1.dist-info/METADATA
axpsystems-0.0.1.dist-info/WHEEL
axpsystems-0.0.1.dist-info/RECORD
