Metadata-Version: 2.4
Name: axpsystems
Version: 0.0.1
Summary: Agentic experience platform - axp.systems (alias)
Project-URL: Homepage, https://axp.systems
Author-email: "axp.systems" <hello@axp.systems>
License-Expression: MIT
Keywords: agentic,agents,ai,llm
